odoo9_addon_medical_medicament_us-9.0.1.0.0.99.dev10-py2.7-nspkg.pth
odoo9_addon_medical_medicament_us-9.0.1.0.0.99.dev10.dist-info/DESCRIPTION.rst
odoo9_addon_medical_medicament_us-9.0.1.0.0.99.dev10.dist-info/METADATA
odoo9_addon_medical_medicament_us-9.0.1.0.0.99.dev10.dist-info/RECORD
odoo9_addon_medical_medicament_us-9.0.1.0.0.99.dev10.dist-info/WHEEL
odoo9_addon_medical_medicament_us-9.0.1.0.0.99.dev10.dist-info/metadata.json
odoo9_addon_medical_medicament_us-9.0.1.0.0.99.dev10.dist-info/namespace_packages.txt
odoo9_addon_medical_medicament_us-9.0.1.0.0.99.dev10.dist-info/top_level.txt
odoo_addons/medical_medicament_us/README.rst
odoo_addons/medical_medicament_us/__init__.py
odoo_addons/medical_medicament_us/__openerp__.py
odoo_addons/medical_medicament_us/demo/medical_manufacturer_demo.xml
odoo_addons/medical_medicament_us/demo/medical_medicament_demo.xml
odoo_addons/medical_medicament_us/demo/medical_medicament_gcn_demo.xml
odoo_addons/medical_medicament_us/demo/medical_medicament_ndc_demo.xml
odoo_addons/medical_medicament_us/i18n/es_CO.po
odoo_addons/medical_medicament_us/i18n/pt_BR.po
odoo_addons/medical_medicament_us/models/__init__.py
odoo_addons/medical_medicament_us/models/medical_medicament.py
odoo_addons/medical_medicament_us/models/medical_medicament_gcn.py
odoo_addons/medical_medicament_us/models/medical_medicament_ndc.py
odoo_addons/medical_medicament_us/security/ir.model.access.csv
odoo_addons/medical_medicament_us/static/description/icon.png
odoo_addons/medical_medicament_us/tests/__init__.py
odoo_addons/medical_medicament_us/tests/test_medical_medicament.py
odoo_addons/medical_medicament_us/views/medical_medicament_view.xml
